highnet/__init__.py
highnet/net.py
highnet-0.0.1.dist-info/METADATA
highnet-0.0.1.dist-info/WHEEL
highnet-0.0.1.dist-info/licenses/LICENSE
highnet-0.0.1.dist-info/RECORD
